trainwatch/__init__.py
trainwatch/metrics.py
trainwatch/system.py
trainwatch/watcher.py
trainwatch-0.1.0.dist-info/licenses/LICENSE
trainwatch-0.1.0.dist-info/METADATA
trainwatch-0.1.0.dist-info/WHEEL
trainwatch-0.1.0.dist-info/top_level.txt
trainwatch-0.1.0.dist-info/RECORD
