Metadata-Version: 2.4
Name: trainwatch
Version: 0.1.0
Summary: Monitor PyTorch training health with one line of code
Author-email: Emirkan Beyaz <emirkanbeyaz01@gmail.com>
License: MIT
Project-URL: Homepage, https://github.com/Hords01/trainwatch
Project-URL: Bug Reports, https://github.com/Hords01/trainwatch/issues
Project-URL: Source, https://github.com/Hords01/trainwatch
Project-URL: Documentation, https://github.com/Hords01/trainwatch/blob/main/README.md
Keywords: pytorch,training,monitoring,deep-learning,machine-learning
Classifier: Development Status :: 3 - Alpha
Classifier: Intended Audience :: Developers
Classifier: Intended Audience :: Science/Research
Classifier: License :: OSI Approved :: MIT License
Classifier: Programming Language :: Python :: 3
Classifier: Programming Language :: Python :: 3.8
Classifier: Programming Language :: Python :: 3.9
Classifier: Programming Language :: Python :: 3.10
Classifier: Programming Language :: Python :: 3.11
Classifier: Programming Language :: Python :: 3.12
Classifier: Topic :: Scientific/Engineering :: Artificial Intelligence
Requires-Python: >=3.8
License-File: LICENSE
Requires-Dist: torch>=2.0.0
Requires-Dist: psutil>=5.9.0
Requires-Dist: numpy>=1.24.0
Provides-Extra: dev
Requires-Dist: pytest>=7.0.0; extra == "dev"
Requires-Dist: black>=22.0.0; extra == "dev"
Requires-Dist: isort>=5.0.0; extra == "dev"
Dynamic: license-file
